sdcflows/__init__.py
sdcflows/_version.py
sdcflows/_warnings.py
sdcflows/config.py
sdcflows/conftest.py
sdcflows/fieldmaps.py
sdcflows/transform.py
sdcflows/cli/__init__.py
sdcflows/cli/main.py
sdcflows/cli/parser.py
sdcflows/cli/workflow.py
sdcflows/cli/tests/__init__.py
sdcflows/cli/tests/test_find_estimators.py
sdcflows/data/__init__.py
sdcflows/data/affine.json
sdcflows/data/fmap-any_registration.json
sdcflows/data/fmap-any_registration_testing.json
sdcflows/data/fmap_atlas.nii.gz
sdcflows/data/fmap_atlas_2_MNI152NLin2009cAsym_affine.mat
sdcflows/data/sd_syn.json
sdcflows/data/sd_syn_sloppy.json
sdcflows/data/translation_rigid.json
sdcflows/data/flirtsch/b02b0.cnf
sdcflows/data/flirtsch/b02b0_1.cnf
sdcflows/data/flirtsch/b02b0_2.cnf
sdcflows/data/flirtsch/b02b0_4.cnf
sdcflows/data/flirtsch/b02b0_quick.cnf
sdcflows/interfaces/__init__.py
sdcflows/interfaces/brainmask.py
sdcflows/interfaces/bspline.py
sdcflows/interfaces/epi.py
sdcflows/interfaces/fmap.py
sdcflows/interfaces/reportlets.py
sdcflows/interfaces/utils.py
sdcflows/interfaces/tests/__init__.py
sdcflows/interfaces/tests/test_bspline.py
sdcflows/interfaces/tests/test_epi.py
sdcflows/interfaces/tests/test_fmap.py
sdcflows/interfaces/tests/test_reportlets.py
sdcflows/interfaces/tests/test_utils.py
sdcflows/tests/__init__.py
sdcflows/tests/test_fieldmaps.py
sdcflows/tests/test_transform.py
sdcflows/tests/test_version.py
sdcflows/utils/__init__.py
sdcflows/utils/bimap.py
sdcflows/utils/epimanip.py
sdcflows/utils/misc.py
sdcflows/utils/phasemanip.py
sdcflows/utils/telemetry.py
sdcflows/utils/tools.py
sdcflows/utils/wrangler.py
sdcflows/utils/tests/__init__.py
sdcflows/utils/tests/test_misc.py
sdcflows/utils/tests/test_phasemanip.py
sdcflows/utils/tests/test_tools.py
sdcflows/utils/tests/test_wrangler.py
sdcflows/viz/__init__.py
sdcflows/viz/utils.py
sdcflows/workflows/__init__.py
sdcflows/workflows/ancillary.py
sdcflows/workflows/base.py
sdcflows/workflows/outputs.py
sdcflows/workflows/apply/__init__.py
sdcflows-2.15.0.dist-info/METADATA
sdcflows-2.15.0.dist-info/WHEEL
sdcflows-2.15.0.dist-info/entry_points.txt
sdcflows-2.15.0.dist-info/licenses/LICENSE
sdcflows-2.15.0.dist-info/RECORD
