Metadata-Version: 2.4
Name: sdcflows
Version: 2.15.0
Summary: Susceptibility Distortion Correction (SDC) workflows for EPI MR schemes.
Project-URL: Documentation, https://www.nipreps.org/sdcflows
Project-URL: Home, https://github.com/nipreps/sdcflows
Project-URL: NiPreps, https://www.nipreps.org/
Author-email: The NiPreps Developers <nipreps@gmail.com>
License-Expression: Apache-2.0
License-File: LICENSE
Classifier: Development Status :: 4 - Beta
Classifier: Intended Audience :: Science/Research
Classifier: License :: OSI Approved :: Apache Software License
Classifier: Programming Language :: Python :: 3.10
Classifier: Programming Language :: Python :: 3.11
Classifier: Programming Language :: Python :: 3.12
Classifier: Programming Language :: Python :: 3.13
Classifier: Topic :: Scientific/Engineering :: Bio-Informatics
Classifier: Topic :: Scientific/Engineering :: Image Recognition
Requires-Python: >=3.10
Requires-Dist: acres>=0.5.0
Requires-Dist: attrs>=20.1.0
Requires-Dist: migas>=0.4.0
Requires-Dist: nibabel>=5.1.1
Requires-Dist: nipype>=1.9.0
Requires-Dist: nireports>=25.0.1
Requires-Dist: nitransforms>=25.0.1
Requires-Dist: niworkflows>=1.14.2
Requires-Dist: numpy>=2.0
Requires-Dist: pybids>=0.16.4
Requires-Dist: scikit-image>=0.23
Requires-Dist: scipy>=1.10
Requires-Dist: templateflow>=23.1
Requires-Dist: toml>=0.10
Provides-Extra: all
Requires-Dist: attrs>=20.1.0; extra == 'all'
Requires-Dist: coverage[toml]>=7; extra == 'all'
Requires-Dist: furo; extra == 'all'
Requires-Dist: importlib-resources; extra == 'all'
Requires-Dist: ipykernel; extra == 'all'
Requires-Dist: ipython; extra == 'all'
Requires-Dist: nbsphinx; extra == 'all'
Requires-Dist: pandoc; extra == 'all'
Requires-Dist: pre-commit; extra == 'all'
Requires-Dist: psutil; extra == 'all'
Requires-Dist: pydot>=1.2.3; extra == 'all'
Requires-Dist: pydotplus; extra == 'all'
Requires-Dist: pytest-cov>=2.11; extra == 'all'
Requires-Dist: pytest-env; extra == 'all'
Requires-Dist: pytest-xdist>=2.5; extra == 'all'
Requires-Dist: pytest>=8.1; extra == 'all'
Requires-Dist: ruff; extra == 'all'
Requires-Dist: sphinx-argparse; extra == 'all'
Requires-Dist: sphinx>=7.2.2; extra == 'all'
Requires-Dist: sphinxcontrib-apidoc; extra == 'all'
Provides-Extra: dev
Requires-Dist: pre-commit; extra == 'dev'
Requires-Dist: ruff; extra == 'dev'
Provides-Extra: doc
Requires-Dist: attrs>=20.1.0; extra == 'doc'
Requires-Dist: furo; extra == 'doc'
Requires-Dist: importlib-resources; extra == 'doc'
Requires-Dist: ipykernel; extra == 'doc'
Requires-Dist: ipython; extra == 'doc'
Requires-Dist: nbsphinx; extra == 'doc'
Requires-Dist: pandoc; extra == 'doc'
Requires-Dist: pydot>=1.2.3; extra == 'doc'
Requires-Dist: pydotplus; extra == 'doc'
Requires-Dist: sphinx-argparse; extra == 'doc'
Requires-Dist: sphinx>=7.2.2; extra == 'doc'
Requires-Dist: sphinxcontrib-apidoc; extra == 'doc'
Provides-Extra: docs
Requires-Dist: attrs>=20.1.0; extra == 'docs'
Requires-Dist: furo; extra == 'docs'
Requires-Dist: importlib-resources; extra == 'docs'
Requires-Dist: ipykernel; extra == 'docs'
Requires-Dist: ipython; extra == 'docs'
Requires-Dist: nbsphinx; extra == 'docs'
Requires-Dist: pandoc; extra == 'docs'
Requires-Dist: pydot>=1.2.3; extra == 'docs'
Requires-Dist: pydotplus; extra == 'docs'
Requires-Dist: sphinx-argparse; extra == 'docs'
Requires-Dist: sphinx>=7.2.2; extra == 'docs'
Requires-Dist: sphinxcontrib-apidoc; extra == 'docs'
Provides-Extra: mem
Requires-Dist: psutil; extra == 'mem'
Provides-Extra: test
Requires-Dist: coverage[toml]>=7; extra == 'test'
Requires-Dist: pytest-cov>=2.11; extra == 'test'
Requires-Dist: pytest-env; extra == 'test'
Requires-Dist: pytest-xdist>=2.5; extra == 'test'
Requires-Dist: pytest>=8.1; extra == 'test'
Provides-Extra: tests
Requires-Dist: coverage[toml]>=7; extra == 'tests'
Requires-Dist: pytest-cov>=2.11; extra == 'tests'
Requires-Dist: pytest-env; extra == 'tests'
Requires-Dist: pytest-xdist>=2.5; extra == 'tests'
Requires-Dist: pytest>=8.1; extra == 'tests'
